LICENSE
README.md
setup.py
krawarranger/__init__.py
krawarranger/_about.py
krawarranger/rawarranger.py
krawarranger/rawerrors.py
krawarranger.egg-info/PKG-INFO
krawarranger.egg-info/SOURCES.txt
krawarranger.egg-info/dependency_links.txt
krawarranger.egg-info/requires.txt
krawarranger.egg-info/top_level.txt