Metadata-Version: 2.1
Name: krawarranger
Version: 0.1.2
Summary: Python script for raw-photography and raw-media organization
Home-page: https://github.com/fjmaro/Krawarranger
Author: Francisco José Mata Aroco
Author-email: 
License: License :: OSI Approved :: GNU General Public License v3 or later (GPLv3+)
Platform: UNKNOWN
Classifier: License :: OSI Approved :: GNU General Public License v3 or later (GPLv3+)
Classifier: Topic :: Multimedia
Classifier: Intended Audience :: Developers
Classifier: Programming Language :: Python :: 3
Classifier: Development Status :: 3 - Alpha
Requires-Python: >=3.9, <4
License-File: LICENSE
